Metadata-Version: 2.1
Name: lucija-package
Version: 0.2
Summary: for testing purposes
License-File: LICENSE.txt
